{
  "mapping": {
    "dependsOn": [
      "000-bootstrap"
    ],
    "implementingPaths": [
      {
        "path": "README.md",
        "source": "spec-edge"
      }
    ],
    "resolvedUnits": [
      {
        "locations": [
          {
            "file": "README.md"
          }
        ],
        "ownership": true,
        "sourceField": "establishes",
        "unit": {
          "kind": "file",
          "path": "README.md"
        }
      }
    ],
    "specId": "001-cli-mcp-thesis",
    "specStatus": "approved"
  },
  "schemaVersion": "1.1.0",
  "shardHash": "6d5733b1b155ee7432d710a1558c55336777afbd6c2f325c54b709a207d33403"
}
